{
  "data": [
    {
      "id": "1514273313039675392",
      "text": "Are you interested in learning how this innovative index leverages $cashtag Tweets to reflect how the world’s largest focus group is talking about publicly traded companies? \n\nhttps://t.co/uiPisid4HY"
    },
    {
      "id": "1514273129329139712",
      "text": "In Q1, the S&amp;P 500 Twitter Sentiment Select Equal Weight Index outperformed its benchmark by 173 bps \n\nThe S&amp;P 500 Equal Weight Index declined by 2.72%, while the S&amp;P 500 Twitter Sentiment Select Equal Weight Index declined by 0.99% https://t.co/gXdIm4qWHj"
    },
    {
      "id": "1514272950219804673",
      "text": "In Q1, the S&amp;P 500 Twitter Sentiment Index outperformed its benchmark by 72 bps \n\nThe S&amp;P 500 Index declined by 4.60%, while the S&amp;P 500 Twitter Sentiment Index declined by 3.88% https://t.co/BJQ1LKa3OV"
    },
    {
      "id": "1514272830610759680",
      "text": "In Q1, volatility returned to the stock market, but #YourVoiceYourIndex was heard loud and clear. \n\nWe’d like to share some updates on the vibrant $cashtag conversation on Twitter, and how your Tweets helped S&amp;P Dow Jones power two stock market indices\uD83D\uDC47"
    },
    {
      "id": "1514272664373760002",
      "text": "Last year, Twitter partnered with S&amp;P Dow Jones Indices, to launch a series of indices that tracks the most positively-talked about companies in the S&amp;P 500 Index.\n\nhttps://t.co/vdrOXLvCTY"
    },
    {
      "id": "1513562834243784705",
      "text": "\uD83D\uDD14 Are you interested in using the Twitter API to teach in your course? Join us tomorrow April 12th at 10 am PT to learn how educators teach with the Twitter API and how you can incorporate it in your course! \uD83D\uDCDA⤵️ https://t.co/7B9Iy2ENEC"
    },
    {
      "id": "1512165222001246208",
      "text": "Surface Crypto insights from Twitter data, quickly &amp; easily, with the Twitter API toolkit for Google Cloud: Filtered Stream - a toolkit for real-time ingesting, processing, &amp; analyzing large volumes of Tweets that can be configured in under 60 mins ⬇️\nhttps://t.co/YzrWrB4Xa5"
    },
    {
      "id": "1511757922354663425",
      "text": "Looking to try out the Twitter API v2 but don’t have a developer account yet? Check out the new Twitter API Playground. This new tool delivers real, live data from the Twitter API for anyone curious about our platform.\n\nLearn more ⬇️\nhttps://t.co/p0N21UAKZG"
    },
    {
      "id": "1509259456525193221",
      "text": "\uD83D\uDCE2 Learn how you can get historical Twitter data for research using our new Downloader tool without writing any code.\n\nJoin us tomorrow at 2pm PT on ➡️ https://t.co/GrtBOXh5Y1 https://t.co/uXOgMNLMry"
    },
    {
      "id": "1508565972147326977",
      "text": "Join @andypiper and team this Wednesday for the last installment of our developer Spaces series on custom Tweet card formats.\n\nhttps://t.co/WqsF8hEBSs"
    }
  ],
  "meta": {
    "result_count": 10,
    "newest_id": "1514273313039675392",
    "oldest_id": "1508565972147326977",
    "next_token": "7140dibdnow9c7btw420k0jcw12s28sfjtk26byxaky0n"
  }
}
